mlleak/__init__.py
mlleak/detector.py
mlleak/reporter.py
mlleak-0.1.1.dist-info/licenses/LICENSE
mlleak-0.1.1.dist-info/METADATA
mlleak-0.1.1.dist-info/WHEEL
mlleak-0.1.1.dist-info/top_level.txt
mlleak-0.1.1.dist-info/RECORD
