Metadata-Version: 2.4
Name: mlleak
Version: 0.1.1
Summary: ML Data Leakage & Split Sanity Checker - Detect duplicates, time leakage, and group leakage in train/test splits
Home-page: https://github.com/Thirumurugan240/mlleak
Author: Thirumurugan
Author-email: Thirumurugan <thirumuruganchandru01@gmail.com>
License: MIT
Project-URL: Homepage, https://github.com/Thirumurugan240/mlleak
Project-URL: Documentation, https://github.com/Thirumurugan240/mlleak#readme
Project-URL: Repository, https://github.com/Thirumurugan240/mlleak
Project-URL: Issues, https://github.com/Thirumurugan240/mlleak/issues
Keywords: machine-learning,data-leakage,train-test-split,data-science,ml-validation
Classifier: Development Status :: 4 - Beta
Classifier: Intended Audience :: Developers
Classifier: Intended Audience :: Science/Research
Classifier: License :: OSI Approved :: MIT License
Classifier: Programming Language :: Python :: 3
Classifier: Programming Language :: Python :: 3.8
Classifier: Programming Language :: Python :: 3.9
Classifier: Programming Language :: Python :: 3.10
Classifier: Programming Language :: Python :: 3.11
Classifier: Topic :: Scientific/Engineering :: Artificial Intelligence
Classifier: Topic :: Software Development :: Quality Assurance
Requires-Python: >=3.8
License-File: LICENSE
Requires-Dist: pandas>=1.0.0
Requires-Dist: numpy>=1.18.0
Dynamic: author
Dynamic: home-page
Dynamic: license-file
Dynamic: requires-python
